{
	"configurations" : 
	[
		{
			"directories" : 
			[
				{
					"build" : ".",
					"jsonFile" : "directory-.-Debug-f5ebdc15457944623624.json",
					"minimumCMakeVersion" : 
					{
						"string" : "3.21"
					},
					"projectIndex" : 0,
					"source" : ".",
					"targetIndexes" : 
					[
						0
					]
				}
			],
			"name" : "Debug",
			"projects" : 
			[
				{
					"directoryIndexes" : 
					[
						0
					],
					"name" : "TestLibLinux",
					"targetIndexes" : 
					[
						0
					]
				}
			],
			"targets" : 
			[
				{
					"directoryIndex" : 0,
					"id" : "TestLibLinux::@6890427a1f51a3e7e1df",
					"jsonFile" : "target-TestLibLinux-Debug-8fb05cafd0897330b86f.json",
					"name" : "TestLibLinux",
					"projectIndex" : 0
				}
			]
		}
	],
	"kind" : "codemodel",
	"paths" : 
	{
		"build" : "/home/andrey/CLionProjects/OS/lab2_LinuxLib/TestLibLinux/cmake-build-debug",
		"source" : "/home/andrey/CLionProjects/OS/lab2_LinuxLib/TestLibLinux"
	},
	"version" : 
	{
		"major" : 2,
		"minor" : 3
	}
}
